kafka_scrapy_connect/__init__.py
kafka_scrapy_connect/extensions.py
kafka_scrapy_connect/pipelines.py
kafka_scrapy_connect/spiders.py
kafka_scrapy_connect-2.5.0.dist-info/LICENSE
kafka_scrapy_connect-2.5.0.dist-info/METADATA
kafka_scrapy_connect-2.5.0.dist-info/WHEEL
kafka_scrapy_connect-2.5.0.dist-info/top_level.txt
kafka_scrapy_connect-2.5.0.dist-info/RECORD
