Metadata-Version: 2.1
Name: kafka-scrapy-connect
Version: 2.5.0
Summary: Integrating Scrapy with kafka using the confluent-kafka python client
Home-page: https://github.com/spicyparrot/kafka_scrapy_connect
Keywords: kafka,scrapy,crawling,scraping
Classifier: Development Status :: 5 - Production/Stable
Classifier: Intended Audience :: Developers
Classifier: License :: OSI Approved :: MIT License
Classifier: Programming Language :: Python :: 3.9
Classifier: Programming Language :: Python :: 3.10
Classifier: Programming Language :: Python :: 3.11
License-File: LICENSE
Requires-Dist: scrapy >=2.11.1
Requires-Dist: confluent-kafka >=2.2.0
